data_files/__init__.py
data_files/modules/__init__.py
data_files/modules/aws_resources/__init__.py
data_files/modules/aws_resources/asg.tf
data_files/modules/aws_resources/data.tf
data_files/modules/aws_resources/ebs.tf
data_files/modules/aws_resources/ec2.tf
data_files/modules/aws_resources/eni.tf
data_files/modules/aws_resources/iam_role.tf
data_files/modules/aws_resources/locals.tf
data_files/modules/aws_resources/sg.tf
data_files/modules/aws_resources/vars.tf
data_files/modules/backend/__init__.py
data_files/modules/backend/main.tf
data_files/modules/backend/outputs.tf
data_files/modules/backend/variables.tf
data_files/modules/backend/templates/__init__.py
data_files/modules/backend/templates/policy.json.tpl
data_files/terraform/__init__.py
data_files/terraform/main.tf
data_files/terraform/provider.tf
data_files/terraform/var.tf
data_files/terraform_setup_roles/__init__.py
data_files/terraform_setup_roles/main.tf
data_files/terraform_setup_roles/provider.tf
data_files/terraform_setup_roles/vars.tf
data_files/terraform_setup_roles/policies/__init__.py
data_files/terraform_setup_roles/policies/developer_attached_policy.json
data_files/terraform_setup_roles/policies/developer_permissions_boundary.json
data_files/terraform_setup_roles/policies/developer_terraform_policy.json
data_files/terraform_setup_roles/policies/trust-policy.json
data_files/terraform_setup_roles/policies/user_assume_role_policy.json
data_files/terraform_setup_s3_bucket/__init__.py
data_files/terraform_setup_s3_bucket/main.tf
data_files/terraform_setup_s3_bucket/outputs.tf
data_files/terraform_setup_s3_bucket/variables.tf
iam_validator/Destroy.py
iam_validator/Helper.py
iam_validator/Setup.py
iam_validator/Validator.py
iam_validator/__init__.py
iam_validator/command.py
test/__init__.py
test/test_command.py
iam_validator-0.0.13.dist-info/LICENSE.txt
iam_validator-0.0.13.dist-info/METADATA
iam_validator-0.0.13.dist-info/WHEEL
iam_validator-0.0.13.dist-info/entry_points.txt
iam_validator-0.0.13.dist-info/top_level.txt
iam_validator-0.0.13.dist-info/RECORD
