Metadata-Version: 2.1
Name: iam-validator
Version: 0.0.13
Summary: Lightweight, extensible schema and IAM validation tool for AWS Roles.
Home-page: https://github.com/rubelw/iam-validator
Author: Will Rubel
Author-email: willrubel@gmail.com
License: GPLv3+
Keywords: validation,iam,scp,aws,python
Platform: any
Classifier: Development Status :: 4 - Beta
Classifier: Intended Audience :: Developers
Classifier: Natural Language :: English
Classifier: Operating System :: OS Independent
Classifier: Programming Language :: Python
Classifier: Programming Language :: Python
Classifier: Programming Language :: Python :: 3.6
License-File: LICENSE.txt
Requires-Dist: boto3 (>=1.4.3)
Requires-Dist: requests (>=2.18)
Requires-Dist: Click (>=6.7)
Requires-Dist: PyYAML (>=3.12)
Requires-Dist: configparser (>=3.5.0)
Requires-Dist: pykwalify (>=1.6.1)
Requires-Dist: schema (>=0.6.8)
Requires-Dist: future (>=0.16.0)
Requires-Dist: six (>=1.11.0)
Requires-Dist: pip
Requires-Dist: botocore
